graphi/__about__.py
graphi/__init__.py
graphi/edge.py
graphi/graph.py
graphi/compatibility/__init__.py
graphi/compatibility/python2.py
graphi/compatibility/python3.py
graphi-0.1.0.dist-info/DESCRIPTION.rst
graphi-0.1.0.dist-info/METADATA
graphi-0.1.0.dist-info/RECORD
graphi-0.1.0.dist-info/WHEEL
graphi-0.1.0.dist-info/metadata.json
graphi-0.1.0.dist-info/top_level.txt
